{
  "cssTheme": "Minimal",
  "enabledCssSnippets": [
    "__v4d3r-ui-system",
    "v4d3r-mermaid-tables-plugins-part1",
    "v4d3r-mermaid-tables-plugins-part2",
    "v4d3r-mermaid-tables-plugins-part3",
    "__v4d3r-mermaid-tables-plugins-part1",
    "__v4d3r-mermaid-tables-plugins-part2",
    "__v4d3r-mermaid-tables-plugins-part3",
    "09-dataview",
    "unified-callout-system",
    "tag-customization-system",
    "square-bracket-glow",
    "pur3v4d3r-ultimate-callout-system",
    "metadata-panel-system",
    "___v4d3r-ui-system",
    "__text-rendering-animation-rendering",
    "__v4d3r-mermaid",
    "__v4d3r-plugins",
    "__v4d3r-tables",
    "_dataview",
    "_jetbrains-mono-light",
    "00-folder-tree",
    "01-glowing-headers",
    "callout-icon",
    "callout-mod-12-icon-style-variations",
    "callout-mod-15-premium-card",
    "callout-mod-16-floating-light",
    "callout-mod-card",
    "callout-mod-neon",
    "callout-mod-raised",
    "code-block-fixed",
    "code-block-language-custom",
    "custom-horizontal-rules-",
    "custom-ordered-list-numbers-(colored)-",
    "glassmorphism-sidebar-system",
    "inline-code-system",
    "metadata-panel"
  ],
  "interfaceFontFamily": "JetBrains Mono",
  "textFontFamily": "JetBrains Mono",
  "monospaceFontFamily": "JetBrains Mono",
  "showViewHeader": true,
  "showRibbon": true,
  "baseFontSizeAction": false,
  "nativeMenus": false,
  "baseFontSize": 22,
  "theme": "obsidian",
  "accentColor": "#ff0000"
}